{
  "featured": "42-oceanview-crest-mosman",
  "listings": [
    {
      "id": "42-oceanview-crest-mosman",
      "status": "active",
      "badge": "Just Listed",
      "suburb": "Cammeray",
      "address": "8 Rangers Road",
      "beds": 4,
      "baths": 3,
      "cars": 2,
      "land": 620,
      "house": 520,
      "yearBuilt": 2019,
      "aspect": "North-East, Harbour Views",
      "councilRates": "$4,800 / year",
      "price": "$3,200,000",
      "priceRaw": null,
      "hero": "/assets/images/listings/cammeray-exterio.jpg",
      "cardImage": "/assets/images/listings/cammeray-interior.jpg",
      "images": [
        "assets/images/listing-detail-hero.jpg",
        "assets/images/listing-interior-1.jpg",
        "assets/images/listing-interior-2.jpg",
        "assets/images/listing-interior-3.jpg"
      ],
      "description": [
        "An architectural masterpiece perched above the harbour with panoramic views from every principal room. Designed for those who demand only the exceptional.",
        "This extraordinary residence represents the pinnacle of North Shore luxury living. From the moment you arrive, the sweeping harbour vistas and the quality of construction set a tone of quiet opulence that few homes can match.",
        "The flowing open-plan living and dining spaces connect seamlessly to an expansive entertainer's terrace, where the Sydney Harbour Bridge frames the horizon like living art. The kitchen is a chef's statement — stone benchtops, butler's pantry, and premium European appliances.",
        "The master suite is a sanctuary unto itself, with a walk-in robe, spa ensuite, and uninterrupted water views. Four further bedrooms, each with generous built-ins, ensure every member of the family is accommodated in comfort."
      ],
      "features": [
        "Panoramic harbour and bridge views",
        "Open-plan living connected to entertainer's terrace",
        "Chef's kitchen with butler's pantry",
        "Master suite with spa ensuite and walk-in robe",
        "5 bedrooms, 4 bathrooms",
        "Double lock-up garage",
        "Ducted air conditioning throughout",
        "Smart home automation",
        "Heated swimming pool",
        "Walking distance to Mosman village"
      ],
      "inspections": [
        "Saturday 19 Apr · 10:00 – 10:30am",
        "Wednesday 23 Apr · 5:00 – 5:30pm",
        "Saturday 26 Apr · 10:00 – 10:30am"
      ],
      "mapEmbed": "https://www.google.com/maps/embed?pb=!1m18!1m12!1m3!1d3313.8!2d151.242!3d-33.828!2m3!1f0!2f0!3f0!3m2!1i1024!2i768!4f13.1!3m3!1m2!1s0x0%3A0x0!2zMzPCsDQ5JzQxLjkiUyAxNTHCsDE0JzMxLjIiRQ!5e0!3m2!1sen!2sau!4v1",
      "nearby": [
        {
          "name": "Mosman Village",
          "distance": "650m",
          "icon": "storefront"
        },
        {
          "name": "Balmoral Beach",
          "distance": "1.2km",
          "icon": "beach_access"
        },
        {
          "name": "Mosman Public School",
          "distance": "800m",
          "icon": "school"
        }
      ],
      "floorPlan": [
        {
          "name": "Master Suite",
          "area": "48 sqm",
          "features": "Ensuite · Walk-in Robe · Harbour Views",
          "left": "0%",
          "top": "0%",
          "width": "42%",
          "height": "45%"
        },
        {
          "name": "Bedroom 2",
          "area": "22 sqm",
          "features": "Built-in Robes · Garden Views",
          "left": "44%",
          "top": "0%",
          "width": "28%",
          "height": "45%"
        },
        {
          "name": "Bedroom 3",
          "area": "20 sqm",
          "features": "Built-in Robes",
          "left": "74%",
          "top": "0%",
          "width": "26%",
          "height": "45%"
        },
        {
          "name": "Living & Dining",
          "area": "72 sqm",
          "features": "Harbour Views · Opens to Terrace",
          "left": "0%",
          "top": "47%",
          "width": "55%",
          "height": "53%"
        },
        {
          "name": "Kitchen",
          "area": "35 sqm",
          "features": "Stone Benchtops · Butler's Pantry",
          "left": "57%",
          "top": "47%",
          "width": "43%",
          "height": "30%"
        },
        {
          "name": "Study",
          "area": "14 sqm",
          "features": "Harbour Views",
          "left": "57%",
          "top": "79%",
          "width": "25%",
          "height": "21%"
        },
        {
          "name": "Bathroom",
          "area": "9 sqm",
          "features": "Full Bath",
          "left": "84%",
          "top": "79%",
          "width": "16%",
          "height": "21%"
        }
      ]
    },
    {
      "id": "12-kurraba-road-neutral-bay",
      "status": "active",
      "badge": "Just Listed",
      "suburb": "Neutral Bay",
      "address": "12 Kurraba Road",
      "beds": 5,
      "baths": 4,
      "cars": 3,
      "land": 540,
      "house": 460,
      "yearBuilt": 2017,
      "aspect": "North, Harbour Views",
      "councilRates": "$4,200 / year",
      "price": "$8,450,000",
      "priceRaw": 8450000,
      "hero": "assets/images/listings/kurraba-hero.jpg",
      "cardImage": "assets/images/listing-neutral-bay.jpg",
      "images": [
        "assets/images/listings/kurraba-hero.jpg",
        "assets/images/listings/kurraba-interior-1.jpg",
        "assets/images/listings/kurraba-interior-2.jpg",
        "assets/images/listings/kurraba-interior-3.jpg",
        "assets/images/listings/kurraba-pool.jpg"
      ],
      "description": [
        "A rare offering in one of Neutral Bay's most coveted streets — 12 Kurraba Road delivers harbour views, exceptional proportions, and effortless indoor-outdoor living.",
        "Positioned on a north-facing block, this five-bedroom residence has been meticulously designed to capture natural light throughout the day. The interiors are both grand in scale and warm in character, with timber flooring, high ceilings, and bespoke joinery throughout.",
        "The kitchen forms the heart of the home — a stunning space with stone island bench, integrated appliances, and a walk-in pantry. It opens to the alfresco dining area and pool terrace, creating a seamless flow perfect for entertaining.",
        "Three of the five bedrooms enjoy harbour glimpses, with the master suite offering a private balcony, walk-in robe, and hotel-quality ensuite. Triple garage, ducted air conditioning, and smart home system complete the picture."
      ],
      "features": [
        "North-facing with harbour views",
        "Heated saltwater pool and terrace",
        "Chef's kitchen with stone island bench",
        "Master suite with private balcony",
        "5 bedrooms, 4 bathrooms",
        "Triple garage with internal access",
        "Ducted reverse-cycle air conditioning",
        "Smart home system",
        "Landscaped gardens by award-winning designer",
        "Moments to Kurraba Point ferry wharf"
      ],
      "inspections": [
        "Saturday 19 Apr · 11:00 – 11:30am",
        "Wednesday 23 Apr · 5:30 – 6:00pm",
        "Saturday 26 Apr · 11:00 – 11:30am"
      ],
      "mapEmbed": "https://www.google.com/maps/embed?pb=!1m18!1m12!1m3!1d3314.2!2d151.224!3d-33.834!2m3!1f0!2f0!3f0!3m2!1i1024!2i768!4f13.1!3m3!1m2!1s0x0%3A0x0!2zMzPCsDUwJzAyLjQiUyAxNTHCsDEzJzI2LjQiRQ!5e0!3m2!1sen!2sau!4v1",
      "nearby": [
        {
          "name": "Kurraba Point Wharf",
          "distance": "400m",
          "icon": "directions_boat"
        },
        {
          "name": "Neutral Bay Village",
          "distance": "900m",
          "icon": "storefront"
        },
        {
          "name": "North Sydney CBD",
          "distance": "2.1km",
          "icon": "business"
        }
      ],
      "floorPlan": [
        {
          "name": "Master Suite",
          "area": "42 sqm",
          "features": "Ensuite · Walk-in Robe · Balcony",
          "left": "0%",
          "top": "0%",
          "width": "45%",
          "height": "45%"
        },
        {
          "name": "Bedroom 2",
          "area": "20 sqm",
          "features": "Built-in Robes · Harbour Views",
          "left": "47%",
          "top": "0%",
          "width": "30%",
          "height": "45%"
        },
        {
          "name": "Bedroom 3",
          "area": "18 sqm",
          "features": "Built-in Robes",
          "left": "79%",
          "top": "0%",
          "width": "21%",
          "height": "45%"
        },
        {
          "name": "Living & Dining",
          "area": "68 sqm",
          "features": "Opens to Pool Terrace",
          "left": "0%",
          "top": "47%",
          "width": "58%",
          "height": "53%"
        },
        {
          "name": "Kitchen",
          "area": "30 sqm",
          "features": "Stone Bench · Walk-in Pantry",
          "left": "60%",
          "top": "47%",
          "width": "40%",
          "height": "32%"
        },
        {
          "name": "Study",
          "area": "12 sqm",
          "features": "Garden Views",
          "left": "60%",
          "top": "81%",
          "width": "40%",
          "height": "19%"
        }
      ]
    },
    {
      "id": "84-milson-road-cremorne-point",
      "status": "active",
      "badge": "Exclusive",
      "suburb": "Cremorne Point",
      "address": "84 Milson Road",
      "beds": 4,
      "baths": 3,
      "cars": 2,
      "land": 480,
      "house": 390,
      "yearBuilt": 2015,
      "aspect": "East, Harbour Views",
      "councilRates": "$3,900 / year",
      "price": "$6,200,000",
      "priceRaw": 6200000,
      "hero": "assets/images/listings/milson-hero.jpg",
      "cardImage": "assets/images/listing-cremorne.jpg",
      "images": [
        "assets/images/listings/milson-hero.jpg",
        "assets/images/listings/milson-interior-1.jpg",
        "assets/images/listings/milson-interior-2.jpg",
        "assets/images/listings/milson-interior-3.jpg",
        "assets/images/listings/milson-garden.jpg"
      ],
      "description": [
        "Perched on the iconic Cremorne Point peninsula, 84 Milson Road is a rare opportunity to secure a beautifully proportioned four-bedroom home with uninterrupted harbour views.",
        "The residence sits in one of Sydney's most tightly-held pockets — Cremorne Point is a car-free peninsula connected to the city by ferry, offering a village pace without sacrificing urban access.",
        "Interiors have been thoughtfully updated whilst retaining the character of the original architecture. Generous living spaces flow to a north-facing terrace that frames the harbour and city skyline in spectacular fashion.",
        "Four bedrooms, a study, and three bathrooms are arranged across two levels, with the master suite commanding the top floor for maximum privacy and views. A double garage and private garden complete this exceptional offering."
      ],
      "features": [
        "Uninterrupted harbour and city skyline views",
        "North-facing entertainer's terrace",
        "Renovated kitchen with European appliances",
        "Master suite occupying entire top floor",
        "4 bedrooms, 3 bathrooms, study",
        "Double lock-up garage",
        "Private landscaped garden",
        "Ferry to CBD in 12 minutes",
        "Walk to Cremorne Point Reserve",
        "Rare car-free peninsula lifestyle"
      ],
      "inspections": [
        "Saturday 19 Apr · 1:00 – 1:30pm",
        "Wednesday 23 Apr · 4:30 – 5:00pm",
        "Saturday 26 Apr · 1:00 – 1:30pm"
      ],
      "mapEmbed": "https://www.google.com/maps/embed?pb=!1m18!1m12!1m3!1d3314.5!2d151.228!3d-33.840!2m3!1f0!2f0!3f0!3m2!1i1024!2i768!4f13.1!3m3!1m2!1s0x0%3A0x0!2zMzPCsDUwJzI0LjAiUyAxNTHCsDEzJzQwLjgiRQ!5e0!3m2!1sen!2sau!4v1",
      "nearby": [
        {
          "name": "Cremorne Point Wharf",
          "distance": "200m",
          "icon": "directions_boat"
        },
        {
          "name": "Cremorne Point Reserve",
          "distance": "300m",
          "icon": "park"
        },
        {
          "name": "Cremorne Village",
          "distance": "1.1km",
          "icon": "storefront"
        }
      ],
      "floorPlan": [
        {
          "name": "Master Suite",
          "area": "38 sqm",
          "features": "Ensuite · Harbour Views · Private Level",
          "left": "0%",
          "top": "0%",
          "width": "60%",
          "height": "50%"
        },
        {
          "name": "Study",
          "area": "10 sqm",
          "features": "Garden Views",
          "left": "62%",
          "top": "0%",
          "width": "38%",
          "height": "50%"
        },
        {
          "name": "Living",
          "area": "55 sqm",
          "features": "Opens to Terrace · Harbour Views",
          "left": "0%",
          "top": "52%",
          "width": "50%",
          "height": "48%"
        },
        {
          "name": "Kitchen",
          "area": "22 sqm",
          "features": "European Appliances",
          "left": "52%",
          "top": "52%",
          "width": "48%",
          "height": "28%"
        },
        {
          "name": "Bedroom 2",
          "area": "18 sqm",
          "features": "Built-in Robes",
          "left": "52%",
          "top": "82%",
          "width": "48%",
          "height": "18%"
        }
      ]
    },
    {
      "id": "22-telegraph-road-pymble",
      "status": "active",
      "badge": "Price on Application",
      "suburb": "Pymble",
      "address": "22 Telegraph Road",
      "beds": 6,
      "baths": 5,
      "cars": 4,
      "land": 1850,
      "house": 680,
      "yearBuilt": 2021,
      "aspect": "North",
      "councilRates": "$5,200 / year",
      "price": "Contact Agent",
      "priceRaw": null,
      "hero": "assets/images/listings/telegraph-hero.jpg",
      "cardImage": "assets/images/listing-pymble.jpg",
      "images": [
        "assets/images/listings/telegraph-hero.jpg",
        "assets/images/listings/telegraph-interior-1.jpg",
        "assets/images/listings/telegraph-interior-2.jpg",
        "assets/images/listings/telegraph-interior-3.jpg",
        "assets/images/listings/telegraph-pool.jpg"
      ],
      "description": [
        "Set on a magnificent 1,850sqm north-facing block, 22 Telegraph Road is one of Pymble's finest contemporary estates — a home of extraordinary scale and quality, built for multi-generational family living.",
        "The bespoke residence was completed in 2021 and showcases the finest in Australian architectural design. Soaring ceilings, floor-to-ceiling glazing, and seamless indoor-outdoor integration define an interior that feels both expansive and intimate.",
        "The entertainer's domain is unrivalled — a vast kitchen with twin islands, a butler's pantry, and direct access to the resort-style pool terrace and landscaped gardens. A dedicated media room, games room, and wine cellar complete the ground floor.",
        "Six bedrooms, each with built-in storage, are arranged across two wings. The master suite is a true retreat with dual walk-in robes, a spa bath, and a private garden courtyard. A four-car garage with workshop space and separate teen retreat complete this extraordinary offering."
      ],
      "features": [
        "1,850sqm north-facing block",
        "Resort-style heated pool and cabana",
        "Twin-island kitchen with butler's pantry",
        "Media room, games room, wine cellar",
        "Master suite with spa bath and courtyard",
        "6 bedrooms, 5 bathrooms",
        "Four-car garage with workshop",
        "Separate teen retreat / granny flat",
        "Full home automation (Crestron)",
        "Moments to Pymble station and GPS"
      ],
      "inspections": [
        "Saturday 19 Apr · 12:00 – 12:30pm",
        "Sunday 20 Apr · 12:00 – 12:30pm",
        "Saturday 26 Apr · 12:00 – 12:30pm"
      ],
      "mapEmbed": "https://www.google.com/maps/embed?pb=!1m18!1m12!1m3!1d3307.2!2d151.140!3d-33.744!2m3!1f0!2f0!3f0!3m2!1i1024!2i768!4f13.1!3m3!1m2!1s0x0%3A0x0!2zMzPCsDQ0JzM4LjQiUyAxNTHCsDA4JzI0LjAiRQ!5e0!3m2!1sen!2sau!4v1",
      "nearby": [
        {
          "name": "Pymble Station",
          "distance": "600m",
          "icon": "train"
        },
        {
          "name": "Pymble Ladies College",
          "distance": "400m",
          "icon": "school"
        },
        {
          "name": "Gordon Village",
          "distance": "1.5km",
          "icon": "storefront"
        }
      ],
      "floorPlan": [
        {
          "name": "Master Suite",
          "area": "55 sqm",
          "features": "Dual Walk-ins · Spa Bath · Courtyard",
          "left": "0%",
          "top": "0%",
          "width": "38%",
          "height": "45%"
        },
        {
          "name": "Bed 2",
          "area": "24 sqm",
          "features": "Built-in Robes · Ensuite",
          "left": "40%",
          "top": "0%",
          "width": "28%",
          "height": "45%"
        },
        {
          "name": "Bed 3",
          "area": "22 sqm",
          "features": "Built-in Robes",
          "left": "70%",
          "top": "0%",
          "width": "30%",
          "height": "45%"
        },
        {
          "name": "Living & Dining",
          "area": "90 sqm",
          "features": "Pool Views · Opens to Terrace",
          "left": "0%",
          "top": "47%",
          "width": "45%",
          "height": "53%"
        },
        {
          "name": "Kitchen",
          "area": "45 sqm",
          "features": "Twin Islands · Butler's Pantry",
          "left": "47%",
          "top": "47%",
          "width": "53%",
          "height": "33%"
        },
        {
          "name": "Media Room",
          "area": "28 sqm",
          "features": "Acoustic Insulation",
          "left": "47%",
          "top": "82%",
          "width": "30%",
          "height": "18%"
        },
        {
          "name": "Wine Cellar",
          "area": "12 sqm",
          "features": "Climate Controlled",
          "left": "79%",
          "top": "82%",
          "width": "21%",
          "height": "18%"
        }
      ]
    }
  ],
  "agent": {
    "name": "James Whitfield",
    "title": "Principal Agent · North Shore Specialist",
    "photo": "assets/images/agent-photo.jpg",
    "phone": "+61290000000",
    "phoneDisplay": "(02) 9000 0000",
    "email": "james@meridianpropertygroup.com.au"
  },
  "office": {
    "name": "Meridian Property Group",
    "address": "124 Military Road, Neutral Bay NSW 2089",
    "phone": "(02) 9000 0000",
    "email": "hello@meridianpropertygroup.com.au",
    "tallyFormId": "FORM_ID"
  }
}
